{"headers":{"plural-forms":"nplurals=4; plural=((n%10==1 && n%100!=11) ? 0 : ((n%10 >= 2 && n%10 <=4 && (n%100 < 12 || n%100 > 14)) ? 1 : ((n%10 == 0 || (n%10 >= 5 && n%10 <=9)) || (n%100 >= 11 && n%100 <= 14)) ? 2 : 3));","language":"ru"},"contexts":{"":{},"Event title":{"(no title)":["(без названия)"]},"Monthly recurring event, repeats on":{"on the first Sunday":["в первое воскресенье"],"on the first Monday":["в первый понедельник"],"on the first Tuesday":["в первый вторник"],"on the first Wednesday":["в первую среду"],"on the first Thursday":["в первый четверг"],"on the first Friday":["в первую пятницу"],"on the first Saturday":["в первую субботу"],"on the second Sunday":["во второе воскресенье"],"on the second Monday":["во второй понедельник"],"on the second Tuesday":["во второй вторник"],"on the second Wednesday":["во вторую среду"],"on the second Thursday":["во второй четверг"],"on the second Friday":["во вторую пятницу"],"on the second Saturday":["во вторую субботу"],"on the third Sunday":["в третье воскресенье"],"on the third Monday":["в третий понедельник"],"on the third Tuesday":["в третий понедельник"],"on the third Wednesday":["в третью среду"],"on the third Thursday":["в третий четверг"],"on the third Friday":["в третью пятницу"],"on the third Saturday":["в третью субботу"],"on the fourth Sunday":["в четвертое воскресенье"],"on the fourth Monday":["в четвертый понедельник"],"on the fourth Tuesday":["в четвертый вторник"],"on the fourth Wednesday":["в четвертый вторник"],"on the fourth Thursday":["в четвертый четверг"],"on the fourth Friday":["в четвертую пятницу"],"on the fourth Saturday":["в четвертую субботу"],"on the last Sunday":["в последнее воскресенье"],"on the last Monday":["в последний понедельник"],"on the last Tuesday":["в последний вторник"],"on the last Wednesday":["в последнюю среду"],"on the last Thursday":["в последний четверг"],"on the last Friday":["в последнюю пятницу"],"on the last Saturday":["в последнюю субботу"],"on day ${ dayOfMonth }":["в день ${ dayOfMonth }"]},"Daily recurring event, frequency":{"${ count } time":["${ count } раз","${ count } раза","${ count } раз","${ count } раз"],"until ${ dateString }":["до ${ dateString }"],"Daily":["Ежедневно"],"Every ${ interval } days":["Каждые ${ interval } дней"],"Daily, ${ timesString }":["Ежедневно, ${ timesString }"],"Every ${ interval } days, ${ timesString }":["Каждые ${ interval } дней в ${ timesString }"],"Daily, ${ untilString }":["Ежедневно, ${ untilString }"],"Every ${ interval } days, ${ untilString }":["Каждые ${ interval } дней до ${ untilString }"]},"Weekly recurring event, repeats on (multiple days), frequency":{"Sunday":["Воскресенье"],"Monday":["Понедельник"],"Tuesday":["Вторник"],"Wednesday":["Среда"],"Thursday":["Четверг"],"Friday":["Пятница"],"Saturday":["Суббота"]},"Weekly recurring event, frequency":{"Weekly on all days":["Еженедельно каждый день"],"Every ${ interval } weeks on all days":["Каждую ${ interval } неделю во все дни"],"Weekly on Sunday":["Еженедельно в воскресенье"],"Every ${ interval } weeks on Sunday":["Каждую ${ interval } неделю в воскресенье"],"Weekly on Monday":["Еженедельно в понедельник"],"Every ${ interval } weeks on Monday":["Каждые ${ interval } недели в понедельник"],"Weekly on Tuesday":["Еженедельно во вторник"],"Every ${ interval } weeks on Tuesday":["Каждые ${ interval } недели во вторник"],"Weekly on Wednesday":["Еженедельно в среду"],"Every ${ interval } weeks on Wednesday":["Каждые ${ interval } недели в среду"],"Weekly on Thursday":["Еженедельно в четверг"],"Every ${ interval } weeks on Thursday":["Каждые ${ interval } недели в четверг"],"Weekly on Friday":["Еженедельно в пятницу"],"Every ${ interval } weeks on Friday":["Каждые ${ interval } недели в пятницу"],"Weekly on Saturday":["Еженедельно в субботу"],"Every ${ interval } weeks on Saturday":["Каждую ${ interval } неделю в субботу"],"Weekly on ${ multipleDaysString }":["Еженедельно в ${ multipleDaysString }"],"Every ${ interval } weeks on ${ multipleDaysString }":["Каждую ${ interval } неделю по ${ multipleDaysString }"],"Weekly on all days, ${ timesString }":["Еженедельно во все дни в ${ timesString }"],"Every ${ interval } weeks on all days, ${ timesString }":["Каждые ${ interval } недели во все дни в ${ timesString }"],"Weekly on Sunday, ${ timesString }":["Еженедельно в воскресенье в ${ timesString }"],"Every ${ interval } weeks on Sunday, ${ timesString }":["Каждые ${ interval } недели по воскресеньям в ${ timesString }"],"Weekly on Monday, ${ timesString }":["Еженедельно в понедельник в ${ timesString }"],"Every ${ interval } weeks on Monday, ${ timesString }":["Каждые ${ interval } недели по понедельникам в ${ timesString }"],"Weekly on Tuesday, ${ timesString }":["Еженедельно по вторникам в ${ timesString }"],"Every ${ interval } weeks on Tuesday, ${ timesString }":["Каждые ${ interval } недели по вторникам в ${ timesString }"],"Weekly on Wednesday, ${ timesString }":["Еженедельно по средам в ${ timesString }"],"Every ${ interval } weeks on Wednesday, ${ timesString }":["Каждые ${ interval } недели по средам в ${ timesString }"],"Weekly on Thursday, ${ timesString }":["Еженедельно по четвергам в ${ timesString }"],"Every ${ interval } weeks on Thursday, ${ timesString }":["Каждые ${ interval } недели по четвергам в ${ timesString }"],"Weekly on Friday, ${ timesString }":["Еженедельно по пятницам в ${ timesString }"],"Every ${ interval } weeks on Friday, ${ timesString }":["Каждые ${ interval } недели по пятницам в ${ timesString }"],"Weekly on Saturday, ${ timesString }":["Еженедельно по субботам в ${ timesString }"],"Every ${ interval } weeks on Saturday, ${ timesString }":["Каждые ${ interval } недели по субботам в ${ timesString }"],"Weekly on ${ multipleDaysString }, ${ timesString }":["Еженедельно по следующим дням: ${ multipleDaysString } в ${ timesString }"],"Every ${ interval } weeks on ${ multipleDaysString }, ${ timesString }":["Каждые ${ interval } недели по следующим дням: ${ multipleDaysString } в ${ timesString }"],"Weekly on all days, ${ untilString }":["Еженедельно, каждый день в ${ untilString }"],"Every ${ interval } weeks on all days, ${ untilString }":["Каждые ${ interval } недели, каждый день до ${ untilString }"],"Weekly on Sunday, ${ untilString }":["Еженедельно по воскресеньям до ${ untilString }"],"Every ${ interval } weeks on Sunday, ${ untilString }":["Каждые ${ interval } недель в Воскресенье до ${ untilString }"],"Weekly on Monday, ${ untilString }":["Еженедельно в понедельник до ${ untilString }"],"Every ${ interval } weeks on Monday, ${ untilString }":["Каждые ${ interval } недель по понедельникам до ${ untilString }"],"Weekly on Tuesday, ${ untilString }":["Еженедельно по вторникам до ${ untilString }"],"Every ${ interval } weeks on Tuesday, ${ untilString }":["Каждые ${ interval } недель по вторникам до ${ untilString }"],"Weekly on Wednesday, ${ untilString }":["Еженедельно по средам до ${ untilString }"],"Every ${ interval } weeks on Wednesday, ${ untilString }":["Каждые ${ interval } недель по средам до ${ untilString }"],"Weekly on Thursday, ${ untilString }":["Еженедельно по четвергам до ${ untilString }"],"Every ${ interval } weeks on Thursday, ${ untilString }":["Каждые ${ interval } недель по четвергам до ${ untilString }"],"Weekly on Friday, ${ untilString }":["Еженедельно по пятницам до ${ untilString }"],"Every ${ interval } weeks on Friday, ${ untilString }":["Каждые ${ interval } недель по пятницам до ${ untilString }"],"Weekly on Saturday, ${ untilString }":["Еженедельно по субботам до ${ untilString }"],"Every ${ interval } weeks on Saturday, ${ untilString }":["Каждые ${ interval } недель по субботам до ${ untilString }"],"Weekly on ${ multipleDaysString }, ${ untilString }":["Еженедельно по следующим дням ${ multipleDaysString } до ${ untilString }"],"Every ${ interval } weeks on ${ multipleDaysString }, ${ untilString }":["Каждые ${ interval } недель по следующим дням: ${ multipleDaysString } до ${ untilString }"]},"Monthly recurring event, frequency":{"Monthly ${ onDayString }":["Ежемесячно ${ onDayString }"],"Every ${ interval } months ${ onDayString }":["Каждые ${ interval } месяцев: ${ onDayString }"],"Monthly ${ onDayString }, ${ timesString }":["Ежемесячно по ${ onDayString } в ${ timesString }"],"Every ${ interval } months ${ onDayString }, ${ timesString }":["Каждые ${ interval } месяцев ${ onDayString } числа, в ${ timesString }"],"Monthly ${ onDayString }, ${ untilString }":["Ежемесячно ${ onDayString } числа, до ${ untilString }"],"Every ${ interval } months ${ onDayString }, ${ untilString }":["Каждые ${ interval } месяцев ${ onDayString } числа, до ${ untilString }"]},"Yearly recurring event, frequency":{"Yearly":["Ежегодно"],"Every ${ interval } years":["Каждые ${ interval } лет"],"Yearly, ${ timesString }":["Ежегодно, ${ timesString }"],"Every ${ interval } years, ${ timesString }":["Каждые ${ interval } лет в ${ timesString }"],"Yearly, ${ untilString }":["Ежегодно до ${ untilString }"],"Every ${ interval } years, ${ untilString }":["Каждые ${ interval } лет, до ${ untilString }"]},"Info":{"Custom":["Пользовательский"],"Custom ${ frequencyString }":["Пользовательский ${ frequencyString }"],"Daily":["Ежедневно"],"Monthly ${ onDayString }":["Ежемесячно ${ onDayString }"],"Yearly":["Ежегодно"],"Session timed out.":["Время сессии истекло."],"Servers are unreachable.":["Серверы недоступны."],"Week":["Неделя"],"Loading":["Загрузка"],"Your Proton Account is associated with ${ externalEmailAddressValue }. To use ${ toAppName }, please create an address.":["Ваш аккаунт Proton связан с ${ externalEmailAddressValue }. Чтобы использовать ${ toAppName }, пожалуйста, создайте адрес."],"Loading ${ appName }":["Загрузка ${ appName }"],"Upgrade to a paid plan with multi-user support to add more users to your organization.":["Перейдите на платный тариф с поддержкой большого количества пользователей, чтобы добавить больше пользователей в вашу организацию."],"Upgrade to a paid plan to unlock premium features and increase your storage space.":["Перейдите на платный тариф, чтобы разблокировать платный функционал и увеличить пространство для хранения."],"Made globally - Hosted in Switzerland":["Сделано всем миром, размещено в Швейцарии"],"Version ${ appVersion }":["Версия ${ appVersion }"],"abuse or fraud":["злоупотреблений или мошенничества"],"here":["здесь"],"Account disabled due to ${ abuseOrFraudLink }.":["Учётная запись отключена по причине ${ abuseOrFraudLink }."],"You can find more information and contact us ${ contactLink }.":["Вы можете найти больше информации и связаться с нами ${ contactLink }."],"Your payment details are protected with TLS encryption and Swiss privacy laws.":["Ваши платёжные данные защищены шифрованием TLS и швейцарскими законами о конфиденциальности."],"For Visa, MasterCard and Discover, the 3 digits on the back of your card. For American Express, the 4 digits on the front of your card.":["Для Visa, MasterCard и Discover, 3 цифры на обратной стороне карты. Для American Express 4 цифры на лицевой стороне карты."],"Please verify the payment in the new tab.":["Пожалуйста, подтвердите платёж в новой вкладке."],"We will redirect you to PayPal in a new browser tab to complete this transaction. If you use any pop-up blockers, please disable them to continue.":["Для завершения этой транзакции мы перенаправим вас на сайт PayPal в новой вкладке браузера. Если вы пользуетесь какими-нибудь блокировщиками всплывающих окон, пожалуйста, временно отключите их перед продолжением."],"You must have a credit card or bank account linked with your PayPal account. If your PayPal account doesn't have that, please ${ clickHere }.":["У Вас должна быть кредитная карта или банковский счет, привязанный к Вашей учетной записи PayPal. Если у Вас нет счета, пожалуйста, ${ clickHere }."],"This will enable PayPal to be used to pay for your Proton subscription. We will redirect you to PayPal in a new browser tab. If you use any pop-up blockers, please disable them to continue.":["Это позволит вам оплачивать подписку на Proton через PayPal. Мы перенаправим вас на сайт PayPal в новой вкладке браузера. Если вы пользуетесь какими-нибудь блокировщиками всплывающих окон, пожалуйста, временно отключите их перед продолжением."],"You must have a credit card or bank account linked with your PayPal account in order to add it as a payment method.":["У Вас должна быть кредитная карта или банковский счет, привязанный к Вашей учетной записи PayPal, чтобы добавить его как способ оплаты."],"Amount below minimum (${ amount }).":["Сумма ниже допустимого минимума (${ amount })."],"Bitcoin transactions can take some time to be confirmed (up to 24 hours). Once confirmed, we will add credits to your account. After transaction confirmation, you can pay your invoice with the credits.":["Транзакции Bitcoin могут занять некоторое время для подтверждения (до 24 часов). Сразу после подтверждения мы добавим средства на ваш счёт. После подтверждения транзакции вы сможете оплатить свой счёт, используя баланс."],"After making your Bitcoin payment, please follow the instructions below to upgrade.":["После внесения оплаты Bitcoin, пожалуйста, следуйте согласно указаниям ниже, чтобы произвести улучшение."],"We use 3-D Secure to protect your payments.":["Мы используем 3-D Secure для защиты ваших платежей."],"Your bank requires 3-D Secure verification for security purposes.":["Ваш банк требует проверки 3-D Secure в целях безопасности."],"Verification will open a new tab, please disable any popup blockers. You will not be charged. Any amount used to verify the card will be refunded immediately.":["Для подтверждения оплаты откроется новая вкладка. Пожалуйста, отключите любые блокировщики всплывающих окон. Снятия ваших средств не произойдёт. Любая сумма, используемая для проверки вашей карты, будет немедленно возвращена."],"Verification will open a new tab, please disable any popup blockers.":["Для подтверждения откроется новая вкладка. Пожалуйста, отключите любые блокировщики всплывающих окон."],"You will soon be redirected to PayPal to verify your payment.":["Скоро вы будете перенаправлены на PayPal для подтверждения вашего платежа."],"You will be soon redirected to your bank to verify your payment.":["Вскоре вы будете перенаправлены в ваш банк для подтверждения вашего платежа."],"Please verify the card in the new tab which was opened.":["Пожалуйста, подтвердите карту в новой вкладке, которая была открыта."],"Please verify payment at the new tab which was opened.":["Пожалуйста, подтвердите оплату в новой вкладке, которая была открыта."],"Verification can take a few minutes.":["Проверка может занять несколько минут."],"Payment can take a few minutes to fully verify.":["Полная проверка платежа может занять несколько минут."],"Please try again, use a different payment method, or contact PayPal for assistance.":["Пожалуйста, попробуйте ещё раз, используйте другой способ оплаты или свяжитесь с PayPal для получения помощи."],"Please try again, use a different payment method, or call your bank for assistance.":["Пожалуйста, попробуйте ещё раз, используйте другой способ оплаты или обратитесь в ваш банк за помощью."],"Since you're an early access user, your account has additional features enabled.":["Так как вы участвуете в программе раннего доступа, для вашей учетной записи появился длополнительный функционал."],"By downgrading to a Free plan, you will permanently lose these benefits, even if you upgrade again in the future.":["Перейдя на бесплатный тарифный план, вы навсегда потеряете эти преимущества, даже если в будущем вы снова улучшите его."],"+${ bonusSpace } bonus storage":["+${ bonusSpace } бонуса к вашему хранилищу"],"+${ organization.BonusVPN } connections for ProtonVPN (allows you to connect more devices to VPN)":["+${ organization.BonusVPN } бонусных ВПН-соедирнений для ProtonVPN (позволяет большему количеству устройств одновременно подключаться к ВПН)"],"Included":["Включено"],"Selected":["Выбрано"],"Support for file sharing protocols such as BitTorrent.":["Поддержка протоколов обмена файлами, таких как Bittorrent."],"Defends against threats to VPN privacy by passing your Internet traffic through multiple servers.":["Защищает от угроз конфиденциальности VPN, передавая ваш интернет-трафик через несколько серверов."],"Route your Internet traffic through the Tor network with a single click.":["Отправляет весь ваш трафик через сеть Tor одним щелчком."],"Access geo-blocked content (Netflix, Amazon Prime Video, BBC iPlayer, Wikipedia, Facebook, YouTube, etc) no matter where you are.":["Доступ к гео-блокированному содержимому (Netflix, Amazon Prime Video, BBC iPlayer, Wikipedia, Facebook, Youtube и т. д.) независимо от того, где Вы находитесь."],"Get access to all the paid features for both ProtonVPN and ProtonMail (the encrypted email service that millions use to protect their data) with one plan.":["Получите доступ ко всем платным функциям ProtonVPN и ProtonMail (зашифрованный сервис электронной почты, который миллионы пользователей используют для защиты своих данных) в рамках одного тарифного плана."],"Save 20% by switching to ${ annualBilling }.":["Сэкономьте 20%, переключившись на ${ annualBilling }."],"Your account is being upgraded, this may take up to 30 seconds.":["Ваша учётная запись улучшается, это может занять до 30 секунд."],"Thank you for supporting our mission.":["Спасибо за поддержку нашей миссии."],"Your account will be updated once the payment is cleared.":["Ваш аккаунт будет обновлен, когда платеж будет проверен."],"Your account has been successfully updated.":["Ваш аккаунт был успешно обновлен."],"Download your favorite app today and take privacy with you everywhere you go.":["Скачайте ваше любимое приложение сегодня и конфиденциальность будет с вами, куда бы вы ни пошли."],"ProtonMail Free":["Бесплатная версия ProtonMail"],"ProtonVPN Free":["Бесплатная версия ProtonVPN"],"ProtonDrive":["ProtonDrive"],"Save 20% by switching to annual billing":["Сэкономьте 20%, переключившись на ежегодную оплату"],"You are saving 20% with annual billing":["Вы экономите 20% при оплате за год"],"You are saving 33% with 2-year billing":["Вы экономите 33% с при оплате за два года"],"Save an extra 20% by combining Mail and VPN":["Сэкономьте дополнительно 20% от суммы, оплачивая Mail и VPN вместе"],"You are saving an extra 20% with the bundle discount":["Вы экономите 20% со скидкой на комплект"],"30-days money back guaranteed":["30-дневная гарантия возврата денег"],"Payments are protected with TLS encryption and Swiss privacy laws":["Платежи защищены шифрованием TLS и швейцарскими законами о конфиденциальности"],"You can use any of your saved payment method or add a new one. Please note that depending on the total amount due, some payment options may not be available.":["Вы можете использовать любой сохраненный способ оплаты или добавить новый. Учтите, что доступность вариантов оплаты зависит от суммы."],"No payment is required at this time.":["В данный момент оплата не требуется."],"Please note that upon clicking the Confirm button, your account will have ${ creditsRemaining } credits remaining.":["Пожалуйста, учтите, что после нажатия на кнопку \"Подтвердить\" в аккаунте останется ${ creditsRemaining } кредитов."],"20% discount applied to your subscription with coupon ${ code }":["К вашей подписке купоном ${ code } применена скидка 20%"],"Black Friday 2018 applied to your subscription":["Чёрная пятница 2018 применена к вашей подписке"],"Black Friday 2019 applied to your subscription":["Чёрная пятница 2019 применена к вашей подписке"],"Black Friday 2020 newcomer discount has been applied":["Мы применили скидку для новых пользователей на черную пятницу 2020"],"Discount applied to your subscription with coupon ${ code }":["К вашей подписке купоном ${ code } применена скидка"],"Expired":["Истёк"],"Your account has at least one overdue invoice. Your access has been restricted. ${ payInvoiceLink }":["Для вашей учетной записи есть по крайней мере один просроченный счет. Ваш доступ был ограничен. ${ payInvoiceLink }"],"Your account has at least one overdue invoice. Your access will soon get restricted. ${ payInvoiceLink }":["Ваша учетная запись имеет по крайней мере один просроченный счет. Ваш доступ скоро будет ограничен. ${ payInvoiceLink }"],"Account access restricted due to unpaid invoices. Please contact your administrator.":["Доступ к учётной записи ограничен из-за неоплаченных счетов. Пожалуйста, обратитесь к вашему администратору."],"Free up some space or add more storage space.":["Освободите место или добавьте больше места."],"Free up some space or contact your administrator.":["Освободите место или свяжитесь с вашим администратором."],"You reached 100% of your storage capacity. You cannot send or receive new emails. ${ freeUpMessage } ${ upgradeLink }":["Вы использовали 100% доступного места. Вы не можете отправлять или получать новые сообщения. ${ freeUpMessage } ${ upgradeLink }"],"You reached ${ spaceDisplayed }% of your storage capacity. ${ freeUpMessage } ${ upgradeLink }":["Вы достигли ${ spaceDisplayed }% емкости Вашего хранилища. ${ freeUpMessage } ${ upgradeLink }"],"You are currently signed in as ${ user.Name } (${ user.Email }) and have restricted access.":["В настоящее время вы вошли как ${ user.Name } (${ user.Email }), и Ваш доступ ограничен."],"Internet connection restored.":["Соединение с интернет восстановлено."],"Servers are unreachable. ${ retryNow }.":["Серверы недоступны. ${ retryNow }."],"Internet connection lost. Please check your device's connectivity.":["Интернет-соединение потеряно. Пожалуйста, проверьте возможность подключения устройства."],"Your Proton account is currently on hold. To continue using your account, please pay any overdue invoices.":["Сейчас Ваш аккаунт Proton приостановлен. Чтобы продолжить использование вашего аккаунта, пожалуйста, оплатите просроченные счета."],"Click \"Request new code\" to have a new verification code sent to ${ strongEmail }. If this email address is incorrect, click \"Edit\" to correct it.":["Нажмите \"Запросить новый код\", и мы отправим новый проверочный код на ${ strongEmail }. Если этот адрес электронной почты не верный, то выберите \"Изменить\" для корректировки."],"Click \"Request new code\" to have a new verification code sent to ${ strongPhone }. If this phone number is incorrect, click \"Edit\" to correct it.":["Нажмите \"Запросить новый код\", и мы отправим новый проверочный код на номер телефона ${ strongPhone }. Если этот номер телефона не верный, то выберите \"Изменить\" для корректировки."],"Would you like to receive a new verification code or use an alternative verification method?":["Вы хотите получить новый проверочный код или использовать другой метод проверки?"],"Enter the verification code that was sent to ${ destinationText }.":["Введите код подтверждения, отправленный на ${ destinationText }."],"If you don't find the email in your inbox, please check your spam folder.":["Если сообщения нет в папке \"Входящие\" — проверьте, не попало ли оно в папку «спам»."],"If you are having trouble creating your account, please request an invitation and we will respond within one business day.":["Если у вас возникли проблемы с созданием учетной записи, пожалуйста, запросите приглашение и мы ответим в течение одного рабочего дня."],"Your email or phone number will only be used for this one-time verification.":["Ваши адрес электронной почты или номер телефона будут использованы только один раз для проверки."],"To fight spam and abuse, please verify you are human.":["Для предотвращения распространения спама и иных злоупотреблений нашим сервисом, нам нужно убедиться, что вы человек."],"You have a new email":["Вы получили новое письмо"],"Desktop notifications are currently":["Уведомления на рабочем столе"],"Screenshot(s) attached":["Снимки экрана прикреплены"],"Refreshing the page or ${ link } will automatically resolve most issues.":["Обновление страницы или ${ link } автоматически решит большую часть проблем."],"Contact us at ${ criticalEmail } for critical security issues.":["Чтобы сообщить о важных проблемах безопасности, пишите нам на ${ criticalEmail }."],"Manage your calendars":["Управление календарями"],"Loading events":["Загружаем события"],"Discard changes?":["Отменить изменения?"],"You will lose all unsaved changes.":["Вы потеряете все несохраненные изменения."],"Delete event":["Удалить событие"],"The organizer of this event will be notified that you decline the invitation. Would you like to delete this event?":["Организатор этого события будет уведомлен о том, что вы отклонили приглашение. Вы хотите удалить это событие?"],"Would you like to delete this event?":["Вы хотите удалить это событие?"],"This event has been updated. The organizer will be notified that you decline the invitation. Would you like to delete this event?":["Событие было обновлено. Организатор будет уведомлен о том, что вы отклонили приглашение. Вы хотите удалить это событие?"],"This event has been updated by the organizer. Would you like to delete this event?":["Это событие было обновлено организатором. Вы хотите удалить это событие?"],"The organizer of this series of events will be notified that you decline the invitation. Would you like to delete all the events in the series?":["Организатор этой серии событий будет уведомлен о том, что вы отклонили приглашение. Вы хотите удалить все события в этой серии?"],"Would you like to delete all the events in the series?":["Вы хотите удалить все события в этой серии?"],"Which event would you like to delete?":["Какое событие вы хотите удалить?"],"Delete recurring event":["Удалить повторяющееся событие"],"This event has been updated by the organizer. Would you like to change your answer only for this event in the series?":["Это событие было обновлено организатором. Вы хотели бы изменить свой ответ только для этого события в серии?"],"Would you like to update this event?":["Вы хотите изменить это событие?"],"Would you like to change your answer for all the events in the series?":["Вы хотите изменить свой ответ для всех событий в серии?"],"Would you like to update all the events in the series?":["Вы хотите изменить все события в этой серии?"],"Which event would you like to update?":["Какое событие вы хотите изменить?"],"Previous modifications on this series will be lost":["Предыдущие изменения в этой серии будут потеряны"],"Frequency modifications will be lost":["Изменения повторения событий будут утеряны"],"The organizer has updated some of the events in this series.\nChanging the calendar is not supported yet for this type of recurring events.":["Организатор обновил некоторые события в этой серии.\nИзменение календаря пока не поддерживается для этого типа повторяющихся событий."],"Update recurring event":["Обновление повторяющегося события"],"You have reset your password and events linked to the following calendars couldn't be decrypted.":["Вы сбросили пароль, и события, связанные со следующими календарями, не могут быть расшифрованы."],"You have reactivated your keys and events linked to the following calendars can now be decrypted.":["Вы повторно активировали свои ключи, и события, связанные со следующими календарями, теперь могут быть расшифрованы."],"Week and month views only apply to desktop.":["Отображение недели и месяца применяются только к рабочему столу."],"Are you sure you want to delete this calendar?":["Вы уверены, что хотите удалить этот календарь?"],"${ calendarName } will be set as default calendar.":["${ calendarName } будет установлен как календарь по умолчанию."],"You need to have an active calendar to import your events.":["Вам нужен активный календарь, чтобы начать импорт событий."],"You can import ICS files from another calendar to ProtonCalendar. This lets you quickly import one event or your entire agenda.":["Вы можете импортировать ICS файлы из другого календаря в ProtonCalendar. Это позволит быстро импортировать одно или все события."],"Import your old messages and folders into ProtonMail.":["Импортируйте ваши старые сообщения и папки в ProtonMail."],"Import your address book or individual contacts into ProtonContacts.":["Импортируйте вашу адресную книгу или отдельные контакты в ProtonContacts."],"Your system time zone seems to have changed to ${ timezone }. Do you want to update your time zone preference?":["Похоже, что ваш часовой пояс изменился на ${ timezone }. Вы хотите обновить настройки часового пояса?"],"Loading event":["Загрузка события"]},"Error":{"Address primary private key not found":["Основной секретный ключ для адреса не найден"],"Calendar primary private key is not decrypted":["Основной секретный ключ календаря не расшифрован"],"Request timed out.":["Истекло время ожидания запроса."],"Signature verification failed":["Сбой проверки подписи"],"Could not find address ${ email }.":["Не могу найти адрес ${ email }."],"Email address disabled":["Эл. адрес отключен"],"No keys retrieved for internal user":["Ключи внутреннего пользователя не получены"],"No valid keys retrieved for internal user":["Действительные ключи внутреннего пользователя не получены"],"Contact signature could not be verified":["Подпись контакта не может быть проверена"],"No key retrieved for internal user is valid for sending":["Ни один их полученных ключей внутреннего пользователя не годен для отправки"],"Trusted keys are not valid for sending":["Доверенные ключи не действительны для отправки"],"No WKD key retrieved for user is valid for sending":["Ни один из полученных WKD ключей пользователя не годен для отправки"],"The sending key is not valid":["Ключ отправки недействительный"],"Missing signature":["Подпись отсутствует"],"Contact signature not verified":["Подпись контакта не проверена"],"Signature not verified":["Подпись не проверена"],"Unknown error":["Неизвестная ошибка"],"Email address invalid":["Неверный адрес электронной почты"],"This field is required":["Это обязательное поле"],"The browser you are using does not allow the payment to be fully authorized. Please use a different browser or log in via a computer.":["Используемый Вами браузер не позволяет совершить платёж. Пожалуйста, используйте другой браузер, либо войдите через компьютер."],"Incorrect mailbox password. Please try again":["Неверный пароль почтового ящика. Пожалуйста, попробуйте снова"],"Incorrect login credentials. Please try again":["Некорректные идентификационные данные. Пожалуйста, попробуйте ещё раз"],"Domain not available, try again later":["Домен недоступен, попробуйте ещё раз позже"],"Can't check username, try again later":["Не могу проверить имя пользователя, попробуйте ещё раз позже"],"Amount below minimum.":["Сумма ниже допустимого минимума."],"Amount above the maximum.":["Сумма выше допустимого максимума."],"Error connecting to the Bitcoin API.":["Ошибка при подключении к Bitcoin API."],"The minimum amount that can be donated is ${ price }":["Минимальная сумма, которую можно пожертвовать, составляет ${ price }"],"The minimum amount of credit that can be added is ${ _price }":["Минимальная сумма, которая может быть добавлена, составляет: ${ _price }"],"The minimum payment we accept is ${ _price2 }":["Минимальная оплата, которую мы принимаем, составляет ${ _price2 }"],"Process aborted":["Процесс прерван"],"Payment process cancelled":["Процесс оплаты отменён"],"Payment process failed":["Сбой в процессе оплаты"],"Payment process consumed":["Процесс оплаты завершён"],"Payment process not supported":["Процесс оплаты не поддерживается"],"Unknown payment token status":["Неизвестный статус платёжного токена"],"Tab closed":["Вкладка закрыта"],"Name on card required":["Требуется имя на карте"],"Invalid expiration date":["Недействительная дата окончания"],"Invalid card number":["Неверный номер карты"],"Invalid ${ name } code":["Недействительный код ${ name }"],"Invalid postal code":["Неверный почтовый индекс"],"Checkout expired, please try again.":["Срок действия заказа истек, попробуйте еще раз."],"Invalid code":["Неверный код"],"The code is not the right length":["Неправильная длина кода"],"Invalid verification code":["Неверный проверочный код"],"Failed to get event":["Не удалось загрузить событие"],"Failed to get original occurrence in series":["Не удалось загрузить начальное вхождение в серию событий"],"It is only possible to move events between ${ minDateString } - ${ maxDateString }":["Перемещать события можно только в интервале ${ minDateString } - ${ maxDateString }"],"It is only possible to create events between ${ minDateString } - ${ maxDateString }":["Создавать события можно только в интервале ${ minDateString } - ${ maxDateString }"],"Invalid link to the event":["Неверная ссылка на событие"],"Primary address key is not decrypted":["Не расшифрован ключ основного адреса"],"No valid address found":["Не найдено действительных адресов"],"Primary address key is not decrypted.":["Не расшифрован ключ основного адреса."],"Please create an address first.":["Пожалуйста, сначала создайте адрес."],"Name required":["Требуется имя"],"Start time must be before end time":["Время начала должно быть раньше времени окончания"],"Interval cannot be empty":["Интервал не может быть пустым"],"Ends on date cannot be empty":["Дата окончания не может быть пустой"],"Ends on date must be after start time":["Дата окончания должна быть позже времени начала"],"Number of occurrences cannot be empty":["Количество повторов не может быть пустым"],"A maximum of 10 notifications is allowed":["Разрешено не более 10 уведомлений"],"Invalid email address":["Неверный адрес электронной почты"],"Decryption error: Decryption of this event's content failed.":["Ошибка расшифровки: не удалось расшифровать содержимое этого события."],"Error: ${ errorMessage }":["Ошибка: ${ errorMessage }"],"Error":["Ошибка"]},"Participant name":{"You":["Вы"]},"PGP key warning":{"Email address not found among user ids defined in sending key (${ keyUserIds })":["Адрес электронной почты не найден среди идентификаторов пользоватеей, определенных в ключе отправки (${ keyUserIds })"]},"file size format":{"bytes":["байт"],"KB":["КБ"],"MB":["МБ"],"GB":["ГБ"]},"Message":{"Re:":["На:"],"Fw:":["Переслано:"]},"Theme":{"Custom mode":["Пользовательский режим"],"Default mode":["Обычный режим"],"Dark mode":["Тёмный режим"]},"Help":{"Use Up and Down keys to access and browse suggestions after input. Press Enter to confirm your choice, or Escape to close the suggestions box.":["Используйте клавиши Вверх и Вниз, чтобы получить доступ и просмотреть предложения после ввода. Нажмите Enter для подтверждения выбора, или Escape для закрытия окна предложений."],"Found ${ numberOfSuggests } suggestion, use keyboard to navigate.":["","","",""]},"Placeholder":{"E.g., ":["Например, "],"e.g. Julia Smith":["например, Джулия Смит"],"Mailbox password":["Пароль почтового ящика"],"Other":["Другое"],"ZIP":["Почтовый индекс"],"Postal code":["Почтовый индекс"],"Gift code":["Подарочный код"],"Enter an email address":["Введите адрес электронной почты"],"Proton username":["Имя пользователя в Proton"],"A way to contact you":["Способ связаться с вами"],"Please describe the problem and include any error messages":["Пожалуйста, опишите проблему и добавьте все возникавшие сообщения об ошибках"],"OS name":["Название ОС"],"OS version":["Версия ОС"],"Browser name":["Название браузера"],"Browser version":["Версия браузера"],"Add a calendar name":["Добавить название календаря"],"Add a calendar description":["Добавить описание календаря"],"Add title":["Добавить название"],"Add participants":["Добавить участников"],"Add location":["Добавить место"],"Add description":["Добавить описание"]},"Label":{"Reveal password":["Показать пароль"],"Hide password":["Скрыть пароль"],"Copy":["Копировать"],"Display name":["Отображаемое имя"],"Username or ProtonMail address":["Имя пользователя или адрес ProtonMail"],"Password":["Пароль"],"Two-factor code":["Код двухфакторной аутентификации"],"Mailbox password":["Пароль почтового ящика"],"Username":["Имя пользователя"],"Cancel":["Отменить"],"Submit":["Отправить"],"Organization":["Организация"],"Storage space":["Место в хранилище"],"Amount":["Сумма"],"Name on card":["Имя на карте"],"Card number":["Номер карты"],"Expiry date":["Срок действия"],"Security code":["Код безопасности"],"Country":["Страна"],"Select your country":["Выберите вашу страну"],"ZIP":["Почтовый индекс"],"Postal code":["Почтовый индекс"],"BTC amount:":["Сумма в биткоинах (BTC):"],"BTC address:":["BTC адрес:"],"Select a method":["Выберите метод"],"Storage space:":["Объём хранилища:"],"Email addresses:":["Адреса электронной почты:"],"Custom domains:":["Пользовательские домены:"],"Users:":["Пользователи:"],"VPN connections:":["VPN-подключения:"],"Proration":["Пропорциональное распределение"],"Cash":["Наличные"],"Card holder":["Владелец карты"],"Expires":["Срок действия"],"Payer":["Плательщик"],"Email address":["Адрес электронной почты"],"Phone number":["Номер телефона"],"Verification code":["Проверочный код"],"Desktop notification":["Уведомление на рабочем столе"],"Proton username":["Имя пользователя в Proton"],"Category":["Категория"],"What happened?":["Что случилось?"],"System information":["Сведения о системе"],"Operating system":["Операционная система"],"Operating system version":["Версия операционной системы"],"Browser":["Браузер"],"Browser version":["Версия браузера"],"Default view":["Вид по умолчанию"],"Week start":["Начало недели"],"Modify in account settings":["Изменить в настройках учетной записи"],"Week numbers":["Номера недель"],"Default event duration":["Длительность события по умолчанию"],"Default notifications":["Стандартные уведомления"],"Default full day notifications":["Стандартные уведомления для событий на весь день"],"Name":["Имя"],"Choose a color":["Выберите цвет"],"Default email":["Эл. почта по умолчанию"],"Display":["Показывать"],"Description":["Описание"],"Optional":["Необязательно"],"All day":["Весь день"],"Repeat on":["Повтор по"],"Repeat every":["Периодичность повтора"],"Ends":["Заканчивается"],"Time of the event":["Время события"],"Event time":["Время события"],"Event title":["Название события"],"Event frequency":["Частота события"],"Participants":["Участники"],"Event location":["Место события"],"Event notifications":["Уведомления о событии"],"Your calendars":["Ваши календари"],"Import to:":["Импортировать в:"]},"Time unit":{"${ hours } hour":["${ hours } час","${ hours } часа","${ hours } часов","${ hours } часов"],"${ minutes } minute":["${ minutes } минута","${ minutes } минуты","${ minutes } минут","${ minutes } минут"]},"Action":{"Close navigation":["Cкрыть панель навигации"],"Open navigation":["Показать панель навигации"],"Close":["Закрыть"],"Next month":["Следующий месяц"],"Prev month":["Предыдущий месяц"],"Delete":["Удалить"],"Yes, I'll attend":["Да, я участвую"],"Maybe I'll attend":["Возможно я участвую"],"No, I won't attend":["Нет, я не участвую"],"Yes":["Да"],"Maybe":["Может быть"],"No":["Нет"],"Go to panel ${ index }":["Перейти к панели ${ index }"],"Confirm":["Подтвердить"],"Cancel":["Отменить"],"Close modal":["Закрыть окно"],"Submit":["Отправить"],"Signing out":["Выйти"],"Need help?":["Нужна помощь?"],"refresh the page":["обновить страницу"],"Upgrade":["Обновление"],"Next":["Далее"],"Back":["Назад"],"Done":["Готово"],"Log in":["Войти"],"Add storage":["Добавить хранилище"],"Manage account":["Управление аккаунтом"],"Switch account":["Переключить учетную запись"],"Proton shop":["Магазин Proton"],"Support us":["Поддержите нас"],"Display mode":["Режим отображения"],"Sign out":["Выйти из учетной записи"],"I have a question":["У меня есть вопрос"],"Request a feature":["Предложить идею"],"Report bug":["Сообщить об ошибке"],"${ BRAND_NAME } introduction":["${ BRAND_NAME } введение"],"Support":["Поддержка"],"Retry":["Повторить"],"Loading verification":["Загружается проверка"],"Try again":["Попробовать снова"],"Verify":["Подтвердить"],"Use a different card":["Использовать другую карту"],"Use a different payment method":["Использовать другой способ оплаты"],"Continue":["Продолжить"],"Donate":["Пожертвовать"],"Remove bonuses":["Удалить бонусы"],"Pay":["Оплатить"],"Hide customization options":["Скрыть настройки"],"Show customization options":["Показать настройки"],"Decrease":["Уменьшить"],"Increase":["Увеличить"],"Select":["Выбрать"],"Customize":["Настроить"],"Show all features":["Показать все функции"],"Upgrade to ProtonMail Plus":["Улучшить до ProtonMail Plus"],"Apply":["Применить"],"Remove gift code":["Удалить подарочный код"],"Retry now":["Повторить сейчас"],"Refresh the page":["Обновить страницу"],"View invoice":["Просмотр счета"],"Edit":["Изменить"],"Request new code":["Запросить новый код"],"Try another method":["Попробуйте другой способ"],"Send code":["Отправить код"],"Did not receive the code?":["Вы не получили код?"],"Change verification":["Изменить способ подтверждения"],"Send test notification":["Отправить тестовое уведомление"],"Enable desktop notification":["Включить уведомление на рабочем столе"],"Clear":["Очистить"],"Add screenshot(s)":["Добавить снимки экрана"],"Hide info":["Скрыть информацию"],"Show info":["Показать информацию"],"New event":["Новое событие"],"Discard":["Отказаться"],"Update":["Обновить"],"Set as default":["Установить по умолчанию"],"Add calendar":["Добавить календарь"],"Import calendar":["Импортировать календарь"],"Select calendar view":["Выберите вид календаря"],"Create":["Создать"],"Import mailbox":["Импортировать почтовый ящик"],"Import contacts":["Импортировать контакты"],"Back to Calendar":["Вернуться в календарь"],"Previous day":["Предыдущий день"],"Previous week":["Предыдущая неделя"],"Previous month":["Предыдущий месяц"],"Previous year":["Предыдущий год"],"Next day":["Следующий день"],"Next week":["Следующая неделя"],"Next year":["Следующий год"],"Today":["Сегодня"],"Select timezone":["Выберите часовой пояс"],"Remove":["Удалить"],"Remove this notification":["Удалить это уведомление"],"Add notification":["Добавить уведомление"],"Hide time zones":["Скрыть часовые пояса"],"Show time zones":["Показать часовые пояса"],"Save":["Сохранить"],"More options":["Доп. настройки"],"Close popover":["Закрыть окно"],"Select file from computer":["Выбрать файл с компьютера"],"Import":["Импортировать"]},"Title":{"Release notes":["Список изменений"],"Change my answer":["Изменить мой ответ"],"Open actions dropdown":["Открыть выпадающее меню со списком действий"],"Create a ProtonMail address":["Создать адрес ProtonMail"],"Plans":["Тарифные планы"],"Default language":["Язык по умолчанию"],"Your organization":["Ваша организация"],"Application settings":["Настройки приложения"],"Account disabled":["Учётная запись отключена"],"Enter your username or ProtonMail email address":["Введите ваше имя пользователя или адрес эл. почты ProtonMail"],"Enter your password":["Введите свой пароль"],"Sign in again to continue":["Чтобы продолжить, повторно войдите ещё раз"],"Settings":["Настройки"],"Toggle display mode":["Переключить режим отображения"],"Back":["Назад"],"Currency":["Валюта"],"ZIP / postal code":["Почтовый индекс"],"Unsupported browser":["Неподдерживаемый браузер"],"Card verification":["Проверка карты"],"Payment verification":["Проверка платежа"],"Processing...":["Обработка..."],"Card verification in progress":["Идёт проверка карты"],"Payment verification in progress":["Производится проверка платежа"],"PayPal verification failed":["Сбой проверки PayPal"],"3-D Secure verification failed":["Сбой проверки 3-D Secure"],"Error":["Ошибка"],"Make a donation":["Сделать пожертвование"],"Confirm loss of Proton bonuses":["Подтвердите потерю бонусов Proton"],"Plan summary":["Сводка по тарифу"],"Configure plan":["Настройка тарифного плана"],"Plans comparison":["Сравнение тарифных планов"],"Subtotal":["Подытог"],"Coupon discount":["Скидка по купону"],"Total (monthly)":["Всего (ежемесячно)"],"Total":["Всего"],"Credits":["Кредиты"],"Gift code":["Подарочный код"],"Amount due":["К оплате"],"Apply gift code":["Применить подарочный код"],"Network error":["Ошибка сети"],"Plan customization":["Настройка плана"],"Checkout":["Расчет"],"Thank you!":["Спасибо!"],"Payment method":["Способ оплаты"],"Billing cycle":["Оплачиваемый период"],"Request new verification code":["Запросить проверочный код"],"Invalid verification code":["Неверный проверочный код"],"Human verification":["Проверка \"Я не робот\""],"Report bug":["Сообщить об ошибке"],"Calendar":["Календарь"],"Reset calendar keys":["Сбросить ключи календаря"],"Reactivate calendar keys":["Повторно активировать ключи календаря"],"Calendar alarm":["Оповещение календаря"],"Delete calendar":["Удалить календарь"],"Time zone":["Часовой пояс"],"Layout":["Макет"],"Desktop notifications":["Уведомления на рабочем столе"],"Update calendar":["Обновить календарь"],"Create calendar":["Создать календарь"],"Calendars":["Календари"],"Import":["Импорт"],"Related features":["Связанные функции"],"Overview":["Обзор"],"Calendar settings":["Настройки календаря"],"Select when you want this notification to be sent":["Выберите, когда вы хотите получать это уведомление"],"Select the time to send this notification":["Выберите время отправки этого уведомления"],"Select the way to send this notification":["Выберите способ отправки этого уведомления"],"Add another notification to remind you of this event":["Добавить другое уведомление, чтобы напомнить вам об этом событии"],"Choose how often this event repeats":["Выберите, как часто повторяется это событие"],"Select event frequency interval":["Выберите интервал частоты события"],"Select a day in the month":["Выберите день месяца"],"Select when this event will stop happening":["Выберите, когда это событие прекратится"],"Select event's last date":["Выберите последнюю дату события"],"Choose how many times this event will repeat":["Выберите, сколько раз это событие будет повторяться"],"Select event start date":["Выберите дату начала события"],"Select event start time":["Выберите время начала события"],"Select the time zone for the event start time":["Выберите часовой пояс для времени начала события"],"Select event end date":["Выберите дату окончания события"],"Select event end time":["Выберите время окончания события"],"Select the time zone for the event end time":["Выберите часовой пояс для времени окончания события"],"Event is happening on defined time slot":["Событие происходит в определенное время"],"Event is happening all day":["Событие происходит весь день"],"Hide time zones for event start and end times":["Не показывать часовые пояса начала и окончания события"],"Show time zones for event start and end times":["Показывать часовые пояса начала и окончания события"],"Add event title":["Добавить название события"],"Select event frequency":["Выберите частоту события"],"Add event location":["Добавить место события"],"Select which calendar to add this event to":["Выберите календарь для добавления этого события"],"Add more information related to this event":["Добавить дополнительную информацию, связанную с этим событием"],"Create event":["Создать событие"],"Edit event":["Изменить событие"],"Event details":["Детали события"],"More options":["Дополнительные параметры"],"CANCELLED":["ОТМЕНЕНО"],"Warning":["Предупреждение"],"Import events":["Импорт событий"]},"Toggle button":{"On":["Вкл"],"Off":["Выкл"],"Normal":["Обычный"],"Dark":["Тёмная"]},"Link":{"Learn more":["Подробнее"],"ProtonMail settings":["Настройки ProtonMail"],"ProtonCalendar settings":["Настройки ProtonCalendar"],"ProtonContacts settings":["Настройки ProtonContacts"],"Manage account":["Управление аккаунтом"],"Terms":["Условия использования"],"Privacy policy":["Политика конфиденциальности"],"Upgrade":["Повысить"],"Reset password":["Сбросить пароль"],"Forgot username?":["Забыли имя пользователя?"],"Common sign in problems":["Распространённые проблемы входа"],"Contact support":["Обратиться в поддержку"],"click here":["нажмите здесь"],"Upgrade to ProtonVPN Plus":["Улучшить до ProtonVPN Plus"],"annual billing":["ежегодное выставление счетов"],"Add a gift code":["Добавить подарочный код"],"Pay invoice":["Оплатить счёт"],"Upgrade account":["Повысить учётную запись"],"Request an invite":["Запросить приглашение"],"clearing your browser cache":["очистка кэша браузера"],"Calendars":["Календари"],"General":["Основные"]},"Countdown status":{"Expired":["Срок действия истек"]},"Countdown unit":{"${ days } day":["${ days } день","${ days } дня","${ days } дней","${ days } дней"],"${ hours } hour":["${ hours } час","${ hours } часа","${ hours } часов","${ hours } часов"],"${ minutes } minute":["${ minutes } минута","${ minutes } минуты","${ minutes } минут","${ minutes } минут"],"${ seconds } second":["${ seconds } секунда","${ seconds } секунды","${ seconds } секунд","${ seconds } секунд"]},"Apps dropdown":{"Proton applications":["Приложения Proton"],"Go to ${ title }":["Перейти к ${ title }"],"Go to ProtonVPN":["Перейти к ProtonVPN"],"Add storage space":["Увеличить объём хранилища"]},"Error message":{"Oops, something went wrong":["Хм. Что-то пошло не так"],"There was a problem connecting to Proton.":["Возникла проблема при подключении к Proton."],"Please ${ refresh } or check your connection.":["Пожалуйста, ${ refresh } или проверьте подключение."],"Brace yourself till we get the error fixed.":["Держитесь, пока мы исправляем ошибку."],"You may also refresh the page or try again later.":["Также вы можете обновить страницу или повторить попытку позже."]},"Organization attribute":{"${ UsedMembers }/${ MaxMembers } active user":["${ UsedMembers } активный пользователь из ${ MaxMembers } ","${ UsedMembers } активных пользователя из ${ MaxMembers }","${ UsedMembers } активных пользователей из ${ MaxMembers }","${ UsedMembers } активных пользователей из ${ MaxMembers }"],"${ UsedDomains }/${ MaxDomains } custom domain":["Использован ${ UsedDomains } пользовательский домен из ${ MaxDomains }","Использованы ${ UsedDomains } пользовательских домена из ${ MaxDomains }","Использованы ${ UsedDomains } пользовательских доменов из ${ MaxDomains }","Использованы ${ UsedDomains } пользовательских доменов из ${ MaxDomains }"]},"Tag":{"Premium feature":["Платный функционал"]},"Onboarding Proton":{"Proton is your private space on the Internet. No one is reading your emails, monitoring your calendar events, or scanning your files. Your data is encrypted, and you’re in control.":["Proton - это ваше личное пространство в Интернете. Никто не читает вашу электронную почту, не отслеживает события в календаре или не сканирует ваши файлы. Ваши данные зашифрованы и вы контролируете всё, что происходит с вашими данными."],"Please choose a display name to finish setting up your account. (Other people will see this.)":["Пожалуйста, выберите отображаемое имя для завершения настройки вашей учетной записи. (Другие пользователи увидят это.)"],"You can quickly open any Proton app from the menu in the top left corner.":["Вы можете быстро открыть любое приложение Proton из меню в левом верхнем углу."],"Click the top right menu to manage your account, log out, switch between your Proton accounts, and toggle light and dark mode.":["Нажмите в верхнем правом меню, чтобы управлять учетной записью, выйти из системы, переключиться между аккаунтами Proton и переключаться между светлым и темным режимами."],"Welcome to privacy":["Добро пожаловать в ваше личное пространство"],"Accessing your Proton Apps":["Доступ к приложениям Proton"],"Manage Your Proton Account":["Управляйте аккаунтом Proton"]},"Signup error":{"Passwords do not match":["Пароль и его подтверждение не совпадают"]},"Header":{"Help":["Помощь"],"Disabled calendars":["Отключённые календари"],"Name":["Имя"],"Status":["Состояние"],"Actions":["Действия"],"Calendar settings":["Настройки календаря"],"Event settings":["Настройки событий"]},"Info for cash payment method":{"Please contact us at ${ email } for instructions on how to pay us with cash.":["Пожалуйста, свяжитесь с нами по ${ email } для получения инструкций по оплате наличными."]},"Success":{"Your support is essential to keeping Proton running. Thank you for supporting internet privacy!":["Ваша поддержка крайне важна для продолжения работы Proton. Благодарим за поддержку конфиденциальности в Интернете!"],"You have successfully unsubscribed":["Подписка успешно отменена"],"Code sent to ${ methodTo }":["Код отправлен на ${ methodTo }"],"Verification successful":["Проверка прошла успешно"],"Bug reported":["Отчёт об ошибке отправлен"],"Preference saved":["Настройки сохранены"],"Default calendar updated":["Основной календарь обновлен"],"Calendar removed":["Календарь удален"],"Calendar created":["Календарь создан"],"Calendar updated":["Календарь обновлен"],"Event created":["Событие создано"],"Participation status updated":["Статус участия обновлен"],"Event updated":["Событие обновлено"],"Answer sent and event deleted":["Ответ отправлен и событие удалено"],"Event deleted":["Событие удалено"],"Events created":["События созданы"],"Future events updated":["Будущие события обновлены"],"Participation status updated for all events":["Статус участия обновлен для всех событий"],"All events updated":["Все события обновлены"],"Answer sent and future events deleted":["Отправленный ответ и все будущие события удалены"],"Future events deleted":["Будущие события удалены"],"Answer sent and all events deleted":["Ответ отправлен и все события удалены"],"All events deleted":["Все события удалены"]},"Suffix":{"/month":["/месяц"],"/month/user":["/месяц/пользователя"]},"Title for subscription plan":{"Current plan":["Текущий тариф"],"Most popular":["Самый популярный"]},"Details":{"Billed as ${ billiedAmount } per year":["Оплачивается ${ billiedAmount } в год"],"Billed as ${ billiedAmount } every 2 years":["Оплачивается ${ billiedAmount } каждые 2 года"]},"Feature":{"1 VPN connection":["1 подключение VPN"],"2 VPN connections":["2 подключения VPN"],"5 VPN connections":["5 подключений VPN"],"10 VPN connections":["10 подключений VPN"],"Servers in ${ vpnCountries.free.length } countries":["Серверы в ${ vpnCountries.free.length } странах"],"Servers in ${ vpnCountries.basic.length } countries":["Серверы в ${ vpnCountries.basic.length } странах"],"Servers in ${ vpnCountries.all.length } countries":["Серверы в ${ vpnCountries.all.length } странах"],"Medium speed":["Средняя скорость"],"High speed":["Высокая скорость"],"Highest speed (up to 10Gbps)":["Наивысшая скорость (до 10Гбит/с)"],"Highest speed (10Gbps)":["Наивысшая скорость (10Гбит/с)"],"Filesharing / P2P":["Файлообмен / P2P"],"Secure Core and Tor VPN":["Secure Core и Tor VPN"],"Advanced privacy features":["Расширенные функции конфиденциальности"],"Access blocked content":["Доступ к заблокированному контенту"],"ProtonMail (optional) *":["ProtonMail (по желанию) *"],"ProtonMail included":["Включая ProtonMail"],"No logs / no ads":["Нет журналов / нет рекламы"],"Perfect Forward Secrecy (PFS)":["Защищенность от чтения назад (Perfect Forward Secrecy)"],"AES-256 encryption":["Шифрование AES-256"],"DNS leak protection":["Защита от утечки DNS"],"Kill Switch":["Kill Switch"],"Always-on VPN":["Постоянный VPN"],"100% anonymous":["100% анонимно"],"10 Gpbs servers":["Серверы 10 Гбит/с"],"Split tunneling support":["Поддержка раздельного туннелирования"],"Swiss based":["Находимся в Швейцарии"],"Professional support":["Профессиональная поддержка"],"1 user":["1 пользователь"],"1 - 5000 users *":["1 - 5000 пользователей *"],"6 users":["6 пользователей"],"0.5 GB storage":["0.5 ГБ хранилища"],"5 GB storage *":["5 ГБ хранилища *"],"5 GB storage / user *":["5 ГБ хранилища на пользователя *"],"20 GB storage":["20 ГБ хранилища"],"1 address":["1 адрес"],"5 addresses *":["5 адресов *"],"5 addresses / user *":["5 адресов на пользователя *"],"50 addresses":["50 адресов"],"No domain support":["Нет поддержки доменов"],"1 custom domain *":["1 свой домен *"],"2 custom domains *":["2 своих домена *"],"10 custom domains":["10 пользовательских доменов"],"150 messages per day":["150 сообщений в день"],"Unlimited messages **":["Неограниченное количество сообщений **"],"3 folders / labels":["3 папки / ярлыка"],"200 folders / labels":["200 папок / ярлыков"],"Unlimited folders / labels":["Неогранич. кол-во папок / ярлыков"],"Limited support":["Ограниченная поддержка"],"Priority support":["Приоритетная поддержка"],"Encrypted contacts":["Зашифрованные контакты"],"Address verification":["Проверка адреса"],"Custom filters":["Настраиваемые фильтры"],"IMAP/SMTP support":["Поддержка IMAP/SMTP"],"Autoresponder":["Автоответчик"],"@pm.me short domain":["Краткий домен @pm.me"],"Catch all email":["Получение всех писем для домена"],"Multi user support":["Поддержка нескольких пользователей"],"ProtonVPN included":["Включая ProtonVPN"],"500 MB storage":["500 МБ хранилища"],"150 messages/day":["150 сообщений в день"],"Advanced mail features: folders, labels, filters, auto-reply, IMAP/SMTP and more":["Расширенные функции почты: папки, ярлыки, фильтры, автоответ, IMAP/SMTP и многое другое"],"Business mail features: Catch all email, multi user management and more":["Функции бизнес-почты: перехват писем всего домена, доступ многих пользователей и другое"],"ProtonVPN (optional) *":["ProtonVPN (по желанию) *"],"Supports 1 domain *":["Поддерживает 1 домен *"],"Unlimited messages per day **":["Неограниченное количество сообщений в день **"],"1 - 5000 user(s) *":["1 - 5000 пользователей *"],"5 GB storage per user *":["5 ГБ хранилища на пользователя *"],"5 addresses per user *":["5 адресов на пользователя *"],"Supports 2 domains *":["Поддерживает 2 домена *"],"Supports 10 domains":["Поддерживает 10 доменов"],"No logs/No ads":["Нет журналов/Нет рекламы"],"Highest speed (up to 10 Gbps)":["Наивысшая скорость (до 10 Гбит/с)"],"All Plus plan features":["Все функции тарифа Plus"],"10 simultaneous VPN connections":["10 одновременных подключений VPN"],"1 email address":["1 адрес эл. почты"],"${ plusAddresses } email addresses":["${ plusAddresses } адресов эл. почты"],"${ plusDomains } custom domain":["${ plusDomains } пользовательский домен","${ plusDomains } пользовательских домена","${ plusDomains } пользовательских доменов","${ plusDomains } пользовательских доменов"],"All Plus features":["Все функции Plus"],"${ professionalMembers } user":["${ professionalMembers } пользователь","${ professionalMembers } пользователя","${ professionalMembers } пользователей","${ professionalMembers } пользователей"],"${ professionalAddresses } email address":["${ professionalAddresses } адрес электронной почты","${ professionalAddresses } адреса электронной почты","${ professionalAddresses } адресов электронной почты","${ professionalAddresses } адресов электронной почты"],"${ professionalDomains } custom domain":["${ professionalDomains } пользовательский домен","${ professionalDomains } пользовательских домена","${ professionalDomains } пользовательских доменов","${ professionalDomains } пользовательских доменов"],"All Professional features":["Все функции Professional"],"50 email addresses":["50 адресов электронной почты"],"All Visionary features":["Все функции Visionary"],"${ vpnCountries.free.length } countries":["${ vpnCountries.free.length } страны"],"Unlimited bandwidth":["Неограниченный трафик"],"${ vpnCountries.basic.length } countries":["${ vpnCountries.basic.length } стран"],"P2P/BitTorrent support":["Поддержка P2P/BitTorrent"],"${ vpnPlusVpn } VPN connections":["${ vpnPlusVpn } VPN-подключений"],"${ vpnCountries.all.length } countries":["${ vpnCountries.all.length } стран"],"Highest speed":["Наивысшая скорость"]},"Info concerning plan features":{"Denotes customizable features":["Обозначает настраиваемые функции"],"ProtonMail cannot be used for mass emailing or spamming. Legitimate emails are unlimited.":["ProtonMail не может быть использован для массовых рассылок или рассылки спама. Для законных электронных писем ограничений нет."],"Customizable features":["Настраиваемые функции"]},"Description":{"Basic private and secure communications":["Простые конфиденциальные и безопасные коммуникации"],"Full-featured individual mailbox":["Полнофункциональный личный почтовый ящик"],"For large organizations and businesses":["Для крупных организаций и предприятий"],"For families and small businesses":["Для семей и малых предприятий"],"Privacy and security for everyone":["Конфиденциальность и безопасность для всех"],"Basic privacy features":["Основные функции конфиденциальности"],"Advanced security features":["Расширенные функции безопасности"],"The complete privacy suite":["Полный набор конфиденциальности"],"You can import events in iCal format (.ics file).\nThe file should have a maximum size of ${ MAX_IMPORT_FILE_SIZE_STRING } and have up to ${ MAX_IMPORT_EVENTS_STRING } events.\nIf your file is bigger, please split it into smaller files.":["Вы можете импортировать события в формате iCal (.ics файл).\nФайл должен иметь максимальный размер ${ MAX_IMPORT_FILE_SIZE_STRING } и иметь до ${ MAX_IMPORT_EVENTS_STRING } событий.\nЕсли ваш файл больше, разделите его на меньшие файлы."]},"Plan feature":{"P2P filesharing/BitTorrent support":["Поддержка P2P файлообмена / BitTorrent"],"Secure Core VPN":["Secure Core VPN"],"Tor over VPN":["Tor через VPN"],"Access blocked content":["Доступ к заблокированному контенту"]},"Plan Feature":{"ProtonMail Visionary account":["Аккаунт ProtonMail Visionary"]},"Description plan":{"To get more features and security, ${ upgradeToPlus }.":["Чтобы получить больше возможностей и безопасности, ${ upgradeToPlus }."],"You can customize the storage, number of addresses, etc, included with ProtonMail Plus.":["В ProtonMail Plus можно настроить емкость хранилища, количество адресов и т. д."],"Select the number of users within your organization.":["Выберите количество пользователей в вашей организации."],"Your plan includes both ProtonMail and ProtonVPN Visionary.":["В Ваш тариф включены и ProtonMail, и ProtonVPN Visionary."],"To get advanced security features and the highest speed, ${ upgradeToVpnPlus }.":["Для получения расширенных функций безопасности и для наивысшей скорости, ${ upgradeToVpnPlus }."],"You can customize the number of connections when combining ProtonVPN with ProtonMail Professional.":["Вы можете настроить количество соединений при комбинировании ProtonVPN с ProtonMail Professional."]},"Decription":{"VPN connections can be allocated to users within your organization. Each device requires one connection.":["VPN-подключения могут быть назначены пользователям внутри вашей организации. Каждое устройство требует одного соединения."],"Each additional user comes automatically with 5 GB storage space and 5 email addresses.":["Каждый дополнительный пользователь автоматически получает 5 ГБ пространства и 5 адресов эл. почты."]},"Status":{"Selected":["Выбрано"]},"Option":{"included":["включено"],"${ value } address":["${ value } адрес","${ value } адреса","${ value } адресов","${ value } адресов"],"${ value } GB storage":["${ value } ГБ хранилища","${ value } ГБ хранилища","${ value } ГБ хранилища","${ value } ГБ хранилища"],"${ value } custom domain":["${ value } пользовательский домен","${ value } пользовательских домена","${ value } пользовательских доменов","{ value } пользовательских доменов"],"${ value } user":["${ value } пользователь","${ value } пользователя","${ value } пользователей","${ value } пользователей"],"${ value } VPN connection":["${ value } VPN-подключение","${ value } VPN подключения","${ value } VPN-подключений","${ value } VPN-подключений"],"This event":["Это событие"],"This and future events":["Это и будущие события"],"All events":["Все события"],"Does not repeat":["Не повторяется"],"Every day":["Каждый день"],"Every week":["Каждую неделю"],"Every month":["Каждый месяц"],"Every year":["Каждый год"],"Custom":["Настроить"],"Day":["День","Дня","Дней","Дней"],"Week":["Неделя","Недели","Недель","Недель"],"Month":["Месяц","Месяца","Месяцев","Месяцев"],"Year":["Год","Года","Лет","Лет"]},"Price":{"Free":["Бесплатно"]},"Addon":{"+ ${ addresses } email addresses":["+ ${ addresses } адрес(а, ов) эл. почты"],"+ ${ storage } storage":["+ ${ storage } хранилища"],"+ ${ domains } custom domain":["+ ${ domains } пользовательский домен","+ ${ domains } пользовательских домена","+ ${ domains } пользовательских доменов","+ ${ domains } пользовательских доменов"],"+ ${ members } user":["+ ${ members } пользователь","+ ${ members } пользователя","+ ${ members } пользователей","+ ${ members } пользователей"],"+ ${ vpn } connection":["+ ${ vpn } подключение","+ ${ vpn } подключения","+ ${ vpn } подключений","+ ${ vpn } подключений"]},"Billing cycle option":{"Monthly":["Ежемесячно"],"Annually SAVE 20%":["Ежегодная ЭКОНОМИЯ 20%"],"Two years SAVE 33%":["Двухлетняя ЭКОНОМИЯ 33%"],"Annually":["Ежегодно"],"Two-year":["Каждые 2 года"]},"Warning":{"Please note that by choosing this payment method, your account cannot be upgraded immediately. We will update your account once the payment is cleared.":["Пожалуйста, обратите внимание, что при выборе этого способа оплаты ваш аккаунт не может быть немедленно обновлен. Мы обновим ваш счет после подтверждения оплаты."],"Bug reports are not end-to-end encrypted, please do not send any sensitive information.":["Сообщения об ошибках не шифруются. Пожалуйста, не отправляйте в них какую-либо конфиденциальную информацию."]},"Tooltip":{"Discount applied for annual billing cycle":["Скидка применена при ежегодной оплате"],"Discount applied for two-year billing cycle":["Скидка применяется при оплате на 2 года вперёд"],"If the system time zone does not match the current time zone preference, you will be asked to update it (at most once per day). ":["Если часовой пояс вашего компьютера не совпадает с текущими настройками часового пояса, мы будем предлагать вам обновить его (не чаще, чем раз в день). "]},"Payment method option":{"Credit/debit card":["Банковская/дебетовая карта"],"PayPal":["PayPal"],"Bitcoin":["Bitcoin"]},"Message display when a new app version is available":{"A new version of ${ appName } is available. ${ reloadButton }.":["Доступна новая версия ${ appName } . ${ reloadButton }."]},"Delinquent modal title":{"Overdue invoice":["Просроченный счёт"]},"Input error":{"This field is required":["Это обязательное поле"]},"Human verification method":{"CAPTCHA":["Капча"],"Email":["Эл. почта"],"SMS":["Короткое сообщение на телефон"],"Manual verification":["Проверить вручную"],"No verification method available":["Нет доступных способов проверки"]},"Desktop notification status":{"Enabled":["Включено"],"Disabled":["Отключено"]},"Error notification in the bug report modal when the user upload file":{"No image selected":["Изображение не выбрано"]},"Bug category":{"Sign in problem":["Проблема со входом"],"Sign up problem":["Проблема при регистрации"],"Payments problem":["Проблема с платежами"],"Custom domain problem":["Проблема своих доменов"],"Bridge problem":["Проблема Bridge"],"Import / export problem":["Проблема импорта / экспорта"],"Connection problem":["Проблема с соединением"],"Slow speed problem":["Проблема: низкая скорость соединения"],"Calendar problem":["Проблема календаря"],"Contacts problem":["Проблема контактов"],"Drive problem":["Проблема Drive"],"Mail problem":["Проблема с почтой"],"VPN problem":["Проблема VPN"],"Feature request":["Запрос новой функции"],"Other":["Другая"],"Signup problem":["Проблема при регистрации"],"Installation problem":["Проблема с установкой ПО"],"Update problem":["Проблема с обновлением"],"Application problem":["Проблема в приложении"],"Speed problem":["Проблема со скоростью"],"Manual setup problem":["Проблема при ручной установке"],"Website access problem":["Проблема с доступом к сайту"],"Streaming problem":["Проблема стриминга"]},"Group":{"Account":["Учётная запись"],"Apps":["Приложения"],"Network":["Сеть"],"Services":["Службы"],"Other category":["Другая категория"]},"Action to select a title for the bug report modal":{"Select":["Выбрать"]},"Label, make it short please":{"Attach screenshot(s)":["Приложить снимки экрана"]},"Alarm notification":{"${ title } starts now":["Событие ${ title } начинается"],"${ title } starts today":["Событие ${ title } начинается сегодня"],"${ title } started at ${ formattedHour }":["Событие ${ title } начинается ${ formattedHour }"],"${ title } started yesterday":["Событие ${ title } началось вчера"],"${ title } started yesterday at ${ formattedHour }":["Событие ${ title } началось вчера в ${ formattedHour }"],"${ title } started on ${ formattedDate }":[""],"${ title } started on ${ formattedDate } at ${ formattedHour }":["Событие ${ title } началось ${ formattedDate } в ${ formattedHour }"],"${ title } started on ${ _formattedDate }":["Событие ${ title } началось ${ _formattedDate }"],"${ title } started on ${ _formattedDate } at ${ formattedHour }":["Событие ${ title } началось ${ _formattedDate } в ${ formattedHour }"],"${ title } started on ${ formattedDateWithoutTime }":["Событие ${ title } началось ${ formattedDateWithoutTime }"],"${ title } started on ${ _formattedDateWithTime }":["Событие ${ title } началось ${ _formattedDateWithTime }"],"${ title } will start at ${ formattedHour }":["Событие ${ title } начнется в ${ formattedHour }"],"${ title } will start tomorrow":["Событие ${ title } начнётся завтра"],"${ title } will start tomorrow at ${ formattedHour }":["Событие ${ title } начинается завтра в ${ formattedHour }"],"${ title } will start on ${ _formattedDate2 }":["Событие ${ title } начинается ${ _formattedDate2 }"],"${ title } will start on ${ _formattedDate2 } at ${ formattedHour }":["Событие ${ title } начинается ${ _formattedDate2 } в ${ formattedHour }"],"${ title } will start on ${ _formattedDate3 }":["Событие ${ title } начинается ${ _formattedDate3 }"],"${ title } will start on ${ _formattedDate3 } at ${ formattedHour }":["Событие ${ title } начнется ${ _formattedDate3 } в ${ formattedHour }"],"${ title } will start on ${ _formattedDateWithoutTime }":["Событие ${ title } начинается ${ _formattedDateWithoutTime }"],"${ title } will start on ${ formattedDateWithTime }":["${ title } начнётся ${ formattedDateWithTime }"],"Requested test will start at 12:00":["Запрошенный тест начнется в 12:00"]},"Error importing event":{"no UID, title or start time":["нет UID, названия или времени начала"],"Component with wrong format":["Компонент с неправильным форматом"],"Non-Gregorian":["Не Грегорианский"],"To-do entry":["Запись списка задач"],"Journal entry":["Запись журнала"],"Free-busy time information":["Информация о свободном и занятом времени"],"Custom timezone":["Настроить часовой пояс"],"Missing UID":["Отсутствует UID"],"Malformed all-day event":["Неправильное оформление события на весь день"],"Missing start time":["Не установлено время начала"],"Malformed start time":["Неправильный формат времени начала"],"Floating times not supported":["Плавающий график не поддерживается"],"Start time out of bounds":["Время начала вне границ"],"Malformed end time":["Неправильный формат времени окончания"],"End time out of bounds":["Время окончания вне границ"],"Event duration not supported":["Длительность события не поддерживается"],"Calendar timezone not supported":["Часовой пояс календаря не поддерживается"],"Timezone not supported":["Часовой пояс не поддерживается"],"Malformed recurring event":["Неправильное повторяющееся событие"],"Recurring rule not supported":["Правило для повторения не поддерживается"],"Edited event not supported":["Отредактированное событие не поддерживается"],"Notification out of bounds":["Уведомление вне границ"],"Event validation failed":["Проверка события не удалась"],"Encryption failed":["Ошибка шифрования"],"Original recurring event could not be found":["Исходное повторяющееся событие не найдено"],"Event":["Событие"],"Calendar":["Календарь"],"Timezone":["Часовой пояс"],"Element":["Элемент"],"Bad format. Component cannot be read.":["Неверный формат. Компонент не может быть прочитан."],"Unknown":["Неизвестно"]},"Event info. Organizer name":{"You":["Вы"]},"Notifications":{"At time of event":["Во время события"],"${ value } minute before":["за ${ value } минуту до","за ${ value } минуты до","за ${ value } минут до","за ${ value } минут до"],"${ value } hour before":["за ${ value } час до","за ${ value } часа до","за ${ value } часов до","за ${ value } часов до"],"${ value } day before":["за ${ value } день до","за ${ value } дня до","за ${ value } дней до","за ${ value } дней до"],"${ value } week before":["за ${ value } неделю до","за ${ value } недели до","за ${ value } недель до","за ${ value } недель до"],"${ value } minute after":["через ${ value } минуту после","через ${ value } минуты после","через ${ value } минут после","через ${ value } минут после"],"${ value } hour after":["через ${ value } час после","через ${ value } часа после","через ${ value } часов после","через ${ value } часов после"],"${ value } day after":["через ${ value } день после","через ${ value } дня после","через ${ value } дней после","через ${ value } дней после"],"${ value } week after":["через ${ value } неделю после","через ${ value } недели после","через ${ value } недель после","через ${ value } недель после"],"Unknown":["Неизвестно"],"On the same day at ${ time }":["В тот же день в ${ time }"],"${ value } minute before at ${ time }":["за ${ value } минуту до в ${ time }","за ${ value } минуты до в ${ time }","за ${ value } минут до в ${ time }","за ${ value } минут до в ${ time }"],"${ value } hour before at ${ time }":["за ${ value } час до в ${ time }","за ${ value } часа до в ${ time }","за ${ value } часов до в ${ time }","за ${ value } часов до в ${ time }"],"${ value } day before at ${ time }":["за ${ value } день до в ${ time }","за ${ value } дня до в ${ time }","за ${ value } дней до в ${ time }","за ${ value } дней до в ${ time }"],"${ value } week before at ${ time }":["за ${ value } неделю до в ${ time }","за ${ value } недели до в ${ time }","за ${ value } недель до в ${ time }","за ${ value } недель до в ${ time }"],"${ value } minute after at ${ time }":["через ${ value } минуту после в ${ time }","через ${ value } минуты после в ${ time }","через ${ value } минут после в ${ time }","через ${ value } минут после в ${ time }"],"${ value } hour after at ${ time }":["через ${ value } час после в ${ time }","через ${ value } часа после в ${ time }","через ${ value } часов после в ${ time }","через ${ value } часов после в ${ time }"],"${ value } day after at ${ time }":["через ${ value } день после в ${ time }","через ${ value } дня после в ${ time }","через ${ value } дней после в ${ time }","через ${ value } дней после в ${ time }"],"${ value } week after at ${ time }":["через ${ value } неделю после в ${ time }","через ${ value } недели после в ${ time }","через ${ value } недель после в ${ time }","через ${ value } недель после в ${ time }"]},"Alert":{"By leaving now, you will lose your event.":["Если выйти сейчас, вы потеряете событие."],"By leaving now, some events may not be imported":["Если выйти сейчас, импорт некоторых событий не завершится"]},"Primary timezone":{"Primary time zone":["Основной часовой пояс"]},"Checkbox":{"Ask to update primary time zone":["Предлагать обновлять основной часовой пояс"],"Show secondary time zone":["Отображать дополнительный часовой пояс"],"Show week numbers":["Отображать номера недель"]},"Secondary timezone":{"Secondary time zone":["Дополнительный часовой пояс"]},"Calendar status":{"Default":["По умолчанию"],"Active":["Активен"],"Disabled":["Отключен"]},"Disabled calendar":{"A calendar is marked as disabled when it is linked to a disabled email address. You can still access your disabled calendar and view events in read-only mode or delete them. You can enable the calendar by re-enabling the email address.":["Календарь отмечен как отключённый, когда он связан с отключённым адресом эл. почты. У вас по-прежнему есть доступ для просмотра событий в календаре или их удаления. Вы можете включить календарь, повторно включив адрес эл. почты."],"Disabled":["Отключен"],"The event belongs to a disabled calendar and you cannot modify it. Please enable your email address again to enable the calendar.":["Событие принадлежит отключённому календарю, и вы не можете изменить его. Пожалуйста, снова включите ваш адрес электронной почты, чтобы включить календарь."]},"Calendar view":{"Day":["День"],"Week":["Неделя"],"Month":["Месяц"]},"Duration":{"30 minutes":["30 минут"],"60 minutes":["60 минут"],"90 minutes":["90 минут"],"120 minutes":["120 минут"]},"Modal title":{"Time zone changed":["Часовой пояс изменен"]},"Notification when":{"day before":["день до","дня до","дней до","дней до"],"on the same day":["тот же день"],"at time of event":["во время события"],"week before":["за неделю","недели до","недель до","недель до"],"minute before":["минуту до","минуты до","минут до","минут до"],"hour before":["час до","часа до","часов до","часов до"]},"Title (number of minutes/hours/days/weeks)":{"Choose a number":["Выберите количество"]},"Notification time input":{"at":["в"]},"Notification type":{"via notification":["с уведомлением "],"by email":["по электронной почте"]},"Event form":{"${ numberOfParticipants } participant":["${ numberOfParticipants } участник","${ numberOfParticipants } участника","${ numberOfParticipants } участников","${ numberOfParticipants } участников"]},"Custom frequency option":{"Never":["Никогда"],"On date…":["До…"],"After repeating…":["После повтора…"],"time":["раз","раза","раз","раз"]},"Calendar invite info":{"${ participantName } accepted the invitation":["${ participantName } принял приглашение"],"${ participantName } tentatively accepted the invitation":["${ participantName } предварительно принял приглашение"],"${ participantName } declined the invitation":["${ participantName } отклонил приглашение"],"${ participantName } hasn't answered the invitation yet":["${ participantName } еще не ответил на приглашение"],"${ name } accepted the invitation":["${ name } принял приглашение"],"${ name } tentatively accepted the invitation":["${ name } предварительно принял приглашение"],"${ name } declined the invitation":["${ name } отклонил приглашение"],"${ name } hasn't answered the invitation yet":["${ name } еще не ответил на приглашение"],"This event has been cancelled":["Это событие было отменено"]},"Event info":{"Organized by:":["Организатор:"]},"Onboarding ProtonCalendar":{"A calendar for your eyes only":["Календарь только для ваших глаз"],"Get ${ appName }":["Используйте ${ appName }"],"Back to your Dashboard":["В панель управления"],"${ appName } is currently in beta and only available to paid users of ${ mailAppName }.":["приложение ${ appName } находится на стадии бета-тестирования и доступно только для платных пользователей ${ mailAppName }."],"To start keeping your plans private now, consider upgrading to a paid plan. ${ appName } will be available to Free plan users when it launches.":["Чтобы начать держать ваши планы в безопасности уже сейчас, подумайте о том, чтобы перейти на платный тариф. ${ appName } будет доступно для пользователей бесплатного тарифа после официального запуска приложения."],"Your secure calendar is ready":["Ваш защищенный календарь готов к использованию"],"Start using ${ appName }":["Начните использовать ${ appName }"],"Import your events":["Импортируйте ваши события"],"ProtonCalendar keeps your plans secure with end-to-end encryption, so we can’t see what you’re doing.":["Ваши данные в ProtonCalendar защищены при помощи сквозного шифрования, и даже мы не можем видеть, что вы делаете."],"We recommend importing your events from your existing calendar. Our import tool is quick and easy, and works with any other provider.":["Мы рекомендуем импортировать ваши события из существующего календаря. Наш помощник по импорту довольно простой и работает быстро с любыми поставщиками сервисов календарей."]},"Error importing calendar":{"An error occurred uploading your file. No file has been selected.":["Произошла ошибка при загрузке вашего файла. Файл не был выбран."],"An error occurred uploading your file ${ formattedFilename }. Only .ics file formats are allowed.":["Произошла ошибка при загрузке файла ${ formattedFilename }. Разрешены только файлы формата .ics."],"Your file ${ formattedFilename } is empty.":["Ваш файл ${ formattedFilename } пуст."],"An error occurred uploading your file ${ formattedFilename }. Maximum file size is ${ MAX_IMPORT_FILE_SIZE_STRING }.":["Произошла ошибка при загрузке файла ${ formattedFilename }. Максимальный размер файла - ${ MAX_IMPORT_FILE_SIZE_STRING }."],"Your file ${ formattedFilename } is not a calendar.":["Ваш файл ${ formattedFilename } не является файлом календаря."],"ProtonCalendar only supports importing calendars with iCal version 2.0.":["ProtonCalendar поддерживает импорт календарей с iCal версии 2.0."],"Your file ${ formattedFilename } is an invitation and cannot be imported.":["Ваш файл ${ formattedFilename } является приглашением и не может быть импортирован."],"Your file ${ formattedFilename } has no events to be imported.":["Ваш файл ${ formattedFilename } не содержит событий для импорта."],"Your file ${ formattedFilename } contains more than ${ MAX_IMPORT_EVENTS_STRING } events.":["Ваш файл ${ formattedFilename } содержит более ${ MAX_IMPORT_EVENTS_STRING } событий."],"An error occurred reading your file ${ formattedFilename }. File does not have the right format.":["Произошла ошибка при чтении вашего файла ${ formattedFilename }. Файл имеет неправильный формат."],"An unexpected error occurred. Import must be restarted.":["Произошла непредвиденная ошибка. Импорт должен быть перезапущен."]},"Import calendar":{"Please don't close the tab before the importing process is finished.":["Пожалуйста, не закрывайте вкладку до завершения импорта."],"Encrypting and adding events to your calendar: ${ totalImported }/${ totalToImport }":["Шифруем и добавляем события в ваш календарь: ${ totalImported }/${ totalToImport }"],"Event successfully imported. The imported event will now appear in your calendar.":["Событие успешно импортировано. Импортированное событие теперь появится в вашем календаре.","События успешно импортированы. Импортированные события теперь появятся в вашем календаре.","События успешно импортированы. Импортированные события теперь появятся в вашем календаре.","События успешно импортированы. Импортированные события теперь появятся в вашем календаре."],"An error occurred while encrypting and adding your events. ${ totalImported } out of ${ totalToImport } events successfully imported.":["Произошла ошибка при шифровании и добавлении событий. ${ totalImported } из ${ totalToImport } событий успешно импортированы."],"An error occurred while encrypting and adding your event. No event could be imported.":["Произошла ошибка при шифровании и добавлении вашего события. Событие не может быть импортировано.","Произошла ошибка при шифровании и добавлении ваших событий. События не могут быть импортированы.","Произошла ошибка при шифровании и добавлении ваших событий. События не могут быть импортированы.","Произошла ошибка при шифровании и добавлении ваших событий. События не могут быть импортированы."],"${ totalImported }/${ totalToImport } event encrypted and added to your calendar":["${ totalImported }/${ totalToImport } событие зашифровано и импортировано в ваш календарь","${ totalImported }/${ totalToImport } события зашифрованы и импортированы в ваш календарь","${ totalImported }/${ totalToImport } событий зашифровано и импортировано в ваш календарь","${ totalImported }/${ totalToImport } событий зашифровано и импортировано в ваш календарь"]},"Info on errors":{"Click for details":["Подробнее..."]},"Import calendar warning":{"for now":["пока"],"ProtonCalendar does not support ${ forNow }:":["ProtonCalendar не поддерживает ${ forNow }:"],"Attendees":["Участники"],"Complex recurring rules":["Сложные правила повторений"],"Email notifications":[""],"To-do entries":["Записи списка задач"],"Journal entries":["Записи в журнале"],"Free-busy time information":["Информация о свободном и занятом времени"],"Unofficial or custom timezones":["Неофициальный или пользовательский часовой пояс"],"Non-Gregorian calendars":["Не грегорианские календари"]},"Import warning":{"No event can be imported. Click for details":["Нельзя импортировать события. Нажмите для получения подробной информации"],"Part of your calendar content is not supported and will not be imported":["Часть содержимого вашего календаря не поддерживается и не будет импортирована"],"${ totalEventsDiscarded } out of ${ totalEvents } events will not be imported. Click for details":["${ totalEventsDiscarded } событий из ${ totalEvents } не будут импортированы. Нажмите, чтобы узнать подробности"]},"blackfriday Promo title, need to be short":{"Special offer":["Спецпредложение"]},"blackfriday Info":{"Get early access to our new encrypted drive for FREE by upgrading to a Plus bundle now.":["БЕСПЛАТНО получите ранний доступ к новому облачному хранилищу с шифрованием файлов! Предложение доступно при оформлении комплекта подписок Plus."],"This subscription will automatically renew after 2 years at the same rate until it is cancelled.":["Через 2 года подписка будет автоматически продлена по той же цене, если вы не отмените ее до этого срока."],"Discounts are based on monthly pricing.":["Размер скидки зависит от суммы платежа в месяц."],"Offer valid only for first-time paid subscriptions.":["Предложение действительно только при первом оформлении платной подписки."],"Save ${ percentage }%":["${ percentage } %"],"Includes":["Включает"],"early access to":["ранний доступ к"],"ProtonDrive":["ProtonDrive"],"Free":["Бесплатно"],"Standard price: ${ regularPrice }":["Обычная цена: ${ regularPrice }"]},"blackfriday Title":{"ProtonDrive early access offer":["Получите ранний доступ к ProtonDrive"],"Cyber Monday Sale":["Скидки киберпонедельника"],"Black Friday Sale":["Скидки «черной пятницы»"],"for 1 month":["за 1 месяц"],"for 1 year":["за 1 год"],"for 2 years":["за 2 года"],"Billed as ${ amount } ${ supNotice }":[""],"(${ notice }) Renews after 1 year at a discounted annual price of ${ amount } every year (20% discount).":["(${ notice }) Автопродление через 1 год по сниженной ежегодной цене ${ amount } (скидка 20 %)."],"(${ notice }) Renews after 2 years at a discounted 2-year price of ${ amount } every 2 years (47% discount).":["(${ notice }) Автопродление через 2 года по сниженной цене ${ amount } за 2 года (скидка 47 %)."],"(${ notice }) Renews after 1 year at a discounted annual & bundle price of ${ amount } every year (36% discount).":["(${ notice }) Автопродление через 1 год по сниженной ежегодной цене за комплект подписок — ${ amount } (скидка 36 %)."],"Most popular":["Самое популярное"]},"blackfriday Action":{"Upgrade":["Сменить тариф"],"Get limited-time deal":["Воспользоваться предложением"]},"blackfriday info":{"per month":["в месяц"]}}}